extra/__init__.py
extra/interface.py
extra/lists/__init__.py
extra/lists/circular_linked_list.py
extra/lists/deque.py
extra/lists/doubly_linked_list.py
extra/lists/linked_list.py
extra/lists/priority_queue.py
extra/lists/queue.py
extra/lists/skip_list.py
extra/lists/stack.py
extra/trees/__init__.py
extra/trees/_heap.py
extra/trees/avl.py
extra/trees/binary_tree.py
extra/trees/bst.py
extra/trees/max_heap.py
extra/trees/min_heap.py
extra/trees/radix_trie.py
extra/trees/red_black_tree.py
extra/trees/splay_tree.py
extra/trees/suffix_trie.py
extra/trees/treap.py
extra/trees/tree.py
extra/trees/trie.py
extra_collections-1.0.1.dist-info/LICENSE
extra_collections-1.0.1.dist-info/METADATA
extra_collections-1.0.1.dist-info/WHEEL
extra_collections-1.0.1.dist-info/top_level.txt
extra_collections-1.0.1.dist-info/RECORD
