Metadata-Version: 2.1
Name: extra-collections
Version: 1.0.1
Summary: `extra-collections` (or `extra` for short) is a python3 pacakge that provides an **pythonic**, **intuitive**, and **easy** implementation of the most common data structures used in software projects.
Home-page: https://github.com/Anwarvic/extra-collections
Author: Anwarvic
Author-email: mohamedanwarvic@gmail.com
License: UNKNOWN
Platform: UNKNOWN
Classifier: Programming Language :: Python :: 3.6
Classifier: Programming Language :: Python :: 3.7
Classifier: Programming Language :: Python :: 3.8
Classifier: License :: OSI Approved :: MIT License
Classifier: Operating System :: OS Independent
Classifier: Topic :: Software Development
Classifier: Topic :: Software Development :: Libraries
Classifier: Topic :: Software Development :: Libraries :: Python Modules
Requires-Python: >=3.6
